{
  "symbol": "CHTR",
  "fetchedAt": "2026-04-23T13:53:54.205Z",
  "currentPrice": 251.6,
  "expirations": [
    {
      "expiration": "2027-01-15",
      "selectionReason": "leap",
      "coveredCalls": [
        {
          "label": "conservative",
          "anchor": "p25",
          "anchorPrice": 319.5995886703796,
          "contract": {
            "contractSymbol": "CHTR270115C00320000",
            "expiration": "2027-01-15",
            "daysToExpiry": 267,
            "strike": 320,
            "bid": 14.5,
            "ask": 16.4,
            "lastPrice": 11.5,
            "volume": 13,
            "openInterest": 273,
            "impliedVolatility": 0.434850622253418,
            "inTheMoney": false
          },
          "snapWarning": false,
          "shortDated": false,
          "staticReturnPct": 0.05763116057233705,
          "staticAnnualizedPct": 0.07878417081986151,
          "assignedReturnPct": 0.32949125596184425,
          "assignedAnnualizedPct": 0.4504281214459669,
          "effectiveCostBasis": 237.1,
          "effectiveDiscountPct": 0.05763116057233705
        }
      ],
      "puts": []
    },
    {
      "expiration": "2028-01-21",
      "selectionReason": "leap",
      "coveredCalls": [],
      "puts": []
    }
  ]
}