{
  "symbol": "CHTR",
  "fetchedAt": "2026-04-26T03:16:22.144Z",
  "currentPrice": 180.13,
  "expirations": [
    {
      "expiration": "2027-01-15",
      "selectionReason": "leap",
      "coveredCalls": [
        {
          "label": "conservative",
          "anchor": "p25",
          "anchorPrice": 302.59279642,
          "contract": {
            "contractSymbol": "CHTR270115C00310000",
            "expiration": "2027-01-15",
            "daysToExpiry": 264,
            "strike": 310,
            "bid": 3.6,
            "ask": 5.5,
            "lastPrice": 3.76,
            "volume": 54,
            "openInterest": 218,
            "impliedVolatility": 0.520390538330078,
            "inTheMoney": false
          },
          "snapWarning": false,
          "shortDated": false,
          "staticReturnPct": 0.019985565980125467,
          "staticAnnualizedPct": 0.027631559025552255,
          "assignedReturnPct": 0.7409648587131517,
          "assignedAnnualizedPct": 1.02444005087235,
          "effectiveCostBasis": 176.53,
          "effectiveDiscountPct": 0.019985565980125467
        }
      ],
      "puts": [
        {
          "label": "deep-value",
          "anchor": "p25",
          "anchorPrice": 302.59279642,
          "contract": {
            "contractSymbol": "CHTR270115P00180000",
            "expiration": "2027-01-15",
            "daysToExpiry": 264,
            "strike": 180,
            "bid": 27.2,
            "ask": 29.3,
            "lastPrice": 25.9,
            "volume": 10,
            "openInterest": 938,
            "impliedVolatility": 0.48328153442382815,
            "inTheMoney": false
          },
          "snapWarning": false,
          "shortDated": false,
          "notAssignedReturnPct": 0.1511111111111111,
          "notAssignedAnnualizedPct": 0.20892255892255893,
          "effectiveCostBasis": 152.8,
          "effectiveDiscountPct": 0.15172375506578573,
          "inTheMoney": false
        }
      ]
    },
    {
      "expiration": "2028-01-21",
      "selectionReason": "leap",
      "coveredCalls": [
        {
          "label": "conservative",
          "anchor": "p25",
          "anchorPrice": 302.59279642,
          "contract": {
            "contractSymbol": "CHTR280121C00310000",
            "expiration": "2028-01-21",
            "daysToExpiry": 635,
            "strike": 310,
            "bid": 39,
            "ask": 46,
            "lastPrice": 34.29,
            "volume": 32,
            "openInterest": 23,
            "impliedVolatility": 0.77383649017334,
            "inTheMoney": false
          },
          "snapWarning": false,
          "shortDated": false,
          "staticReturnPct": 0.21651029811802588,
          "staticAnnualizedPct": 0.12445080128044007,
          "assignedReturnPct": 0.9374895908510521,
          "assignedAnnualizedPct": 0.5388719695443055,
          "effectiveCostBasis": 141.13,
          "effectiveDiscountPct": 0.21651029811802588
        }
      ],
      "puts": [
        {
          "label": "deep-value",
          "anchor": "p25",
          "anchorPrice": 302.59279642,
          "contract": {
            "contractSymbol": "CHTR280121P00180000",
            "expiration": "2028-01-21",
            "daysToExpiry": 635,
            "strike": 180,
            "bid": 37,
            "ask": 42.1,
            "lastPrice": 40,
            "volume": 41,
            "openInterest": 48,
            "impliedVolatility": 0.45145201873779295,
            "inTheMoney": false
          },
          "snapWarning": false,
          "shortDated": false,
          "notAssignedReturnPct": 0.20555555555555555,
          "notAssignedAnnualizedPct": 0.11815398075240593,
          "effectiveCostBasis": 143,
          "effectiveDiscountPct": 0.20612890690057178,
          "inTheMoney": false
        }
      ]
    }
  ]
}