{
  "symbol": "CMCSA",
  "fetchedAt": "2026-05-19T16:10:53.732Z",
  "currentPrice": 24.815,
  "expirations": [
    {
      "expiration": "2026-05-22",
      "selectionReason": "weekly",
      "coveredCalls": [],
      "puts": [
        {
          "label": "deep-value",
          "anchor": "p25",
          "anchorPrice": 39.2280861076733,
          "contract": {
            "contractSymbol": "CMCSA260522P00024500",
            "expiration": "2026-05-22",
            "daysToExpiry": 3,
            "strike": 24.5,
            "bid": 0.14,
            "ask": 0.21,
            "lastPrice": 0.18,
            "volume": 31,
            "openInterest": 2918,
            "impliedVolatility": 0.335944140625,
            "inTheMoney": false
          },
          "snapWarning": true,
          "shortDated": true,
          "notAssignedReturnPct": 0.005714285714285715,
          "notAssignedAnnualizedPct": 0.6952380952380953,
          "effectiveCostBasis": 24.36,
          "effectiveDiscountPct": 0.01833568406205931,
          "inTheMoney": false
        }
      ]
    },
    {
      "expiration": "2026-06-18",
      "selectionReason": "monthly",
      "coveredCalls": [
        {
          "label": "conservative",
          "anchor": "p25",
          "anchorPrice": 39.2280861076733,
          "contract": {
            "contractSymbol": "CMCSA260618C00040000",
            "expiration": "2026-06-18",
            "daysToExpiry": 30,
            "strike": 40,
            "bid": 0.01,
            "ask": 0.03,
            "lastPrice": 0.01,
            "volume": 13,
            "openInterest": 294,
            "impliedVolatility": 0.6953155468750001,
            "inTheMoney": false
          },
          "snapWarning": false,
          "shortDated": false,
          "staticReturnPct": 0.004750927272777457,
          "staticAnnualizedPct": 0.05780294848545906,
          "assignedReturnPct": 0.6166791964647983,
          "assignedAnnualizedPct": 7.502930223655046,
          "effectiveCostBasis": 24.805,
          "effectiveDiscountPct": 0.00040298206729800525
        }
      ],
      "puts": [
        {
          "label": "deep-value",
          "anchor": "p25",
          "anchorPrice": 39.2280861076733,
          "contract": {
            "contractSymbol": "CMCSA260618P00024000",
            "expiration": "2026-06-18",
            "daysToExpiry": 30,
            "strike": 24,
            "bid": 0.49,
            "ask": 0.52,
            "lastPrice": 0.5,
            "volume": 98,
            "openInterest": 8634,
            "impliedVolatility": 0.305671005859375,
            "inTheMoney": false
          },
          "snapWarning": true,
          "shortDated": false,
          "notAssignedReturnPct": 0.020416666666666666,
          "notAssignedAnnualizedPct": 0.24840277777777775,
          "effectiveCostBasis": 23.51,
          "effectiveDiscountPct": 0.05258915978238967,
          "inTheMoney": false
        }
      ]
    },
    {
      "expiration": "2027-01-15",
      "selectionReason": "yearly",
      "coveredCalls": [
        {
          "label": "conservative",
          "anchor": "p25",
          "anchorPrice": 39.2280861076733,
          "contract": {
            "contractSymbol": "CMCSA270115C00040000",
            "expiration": "2027-01-15",
            "daysToExpiry": 241,
            "strike": 40,
            "bid": 0.13,
            "ask": 0.17,
            "lastPrice": 0.16,
            "volume": 17,
            "openInterest": 6715,
            "impliedVolatility": 0.348639326171875,
            "inTheMoney": false
          },
          "snapWarning": false,
          "shortDated": false,
          "staticReturnPct": 0.040167260025558996,
          "staticAnnualizedPct": 0.06083423198891715,
          "assignedReturnPct": 0.6520955292175799,
          "assignedAnnualizedPct": 0.9876135608482018,
          "effectiveCostBasis": 24.685000000000002,
          "effectiveDiscountPct": 0.005238766874874068
        }
      ],
      "puts": [
        {
          "label": "deep-value",
          "anchor": "p25",
          "anchorPrice": 39.2280861076733,
          "contract": {
            "contractSymbol": "CMCSA270115P00024000",
            "expiration": "2027-01-15",
            "daysToExpiry": 241,
            "strike": 24,
            "bid": 2.4,
            "ask": 2.68,
            "lastPrice": 2.44,
            "volume": 63,
            "openInterest": 1024,
            "impliedVolatility": 0.38892212646484375,
            "inTheMoney": false
          },
          "snapWarning": true,
          "shortDated": false,
          "notAssignedReturnPct": 0.09999999999999999,
          "notAssignedAnnualizedPct": 0.15145228215767634,
          "effectiveCostBasis": 21.6,
          "effectiveDiscountPct": 0.12955873463630868,
          "inTheMoney": false
        }
      ]
    }
  ]
}