{
  "symbol": "LMT",
  "fetchedAt": "2026-04-23T20:13:38.506Z",
  "currentPrice": 530.02,
  "expirations": [
    {
      "expiration": "2027-01-15",
      "selectionReason": "leap",
      "coveredCalls": [
        {
          "label": "conservative",
          "anchor": "p25",
          "anchorPrice": 757.574108292792,
          "contract": {
            "contractSymbol": "LMT270115C00760000",
            "expiration": "2027-01-15",
            "daysToExpiry": 267,
            "strike": 760,
            "bid": 5,
            "ask": 8.8,
            "lastPrice": 10.1,
            "volume": 7,
            "openInterest": 93,
            "impliedVolatility": 0.3324041369628906,
            "inTheMoney": false
          },
          "snapWarning": false,
          "shortDated": false,
          "staticReturnPct": 0.027209224180378206,
          "staticAnnualizedPct": 0.03719613043385036,
          "assignedReturnPct": 0.4611173785896458,
          "assignedAnnualizedPct": 0.6303664538772311,
          "effectiveCostBasis": 525.02,
          "effectiveDiscountPct": 0.00943360627900834
        }
      ],
      "puts": [
        {
          "label": "deep-value",
          "anchor": "p25",
          "anchorPrice": 757.574108292792,
          "contract": {
            "contractSymbol": "LMT270115P00530000",
            "expiration": "2027-01-15",
            "daysToExpiry": 267,
            "strike": 530,
            "bid": 50.2,
            "ask": 55.1,
            "lastPrice": 51,
            "volume": 12,
            "openInterest": 279,
            "impliedVolatility": 0.3051522122192383,
            "inTheMoney": false
          },
          "snapWarning": false,
          "shortDated": false,
          "notAssignedReturnPct": 0.09471698113207548,
          "notAssignedAnnualizedPct": 0.12948201540527174,
          "effectiveCostBasis": 479.8,
          "effectiveDiscountPct": 0.09475114146635971,
          "inTheMoney": false
        }
      ]
    },
    {
      "expiration": "2028-01-21",
      "selectionReason": "leap",
      "coveredCalls": [
        {
          "label": "conservative",
          "anchor": "p25",
          "anchorPrice": 757.574108292792,
          "contract": {
            "contractSymbol": "LMT280121C00760000",
            "expiration": "2028-01-21",
            "daysToExpiry": 638,
            "strike": 760,
            "bid": 24,
            "ask": 31,
            "lastPrice": 54.24,
            "volume": 1,
            "openInterest": 207,
            "impliedVolatility": 0.328208011932373,
            "inTheMoney": false
          },
          "snapWarning": false,
          "shortDated": false,
          "staticReturnPct": 0.08775638212828113,
          "staticAnnualizedPct": 0.0502054537254273,
          "assignedReturnPct": 0.5216645365375487,
          "assignedAnnualizedPct": 0.29844444488433436,
          "effectiveCostBasis": 506.02,
          "effectiveDiscountPct": 0.04528131013924003
        }
      ],
      "puts": [
        {
          "label": "deep-value",
          "anchor": "p25",
          "anchorPrice": 757.574108292792,
          "contract": {
            "contractSymbol": "LMT280121P00530000",
            "expiration": "2028-01-21",
            "daysToExpiry": 638,
            "strike": 530,
            "bid": 74,
            "ask": 80.6,
            "lastPrice": 77,
            "volume": 3,
            "openInterest": 5,
            "impliedVolatility": 0.2900919380187988,
            "inTheMoney": false
          },
          "snapWarning": false,
          "shortDated": false,
          "notAssignedReturnPct": 0.13962264150943396,
          "notAssignedAnnualizedPct": 0.07987815697640031,
          "effectiveCostBasis": 456,
          "effectiveDiscountPct": 0.13965510735443942,
          "inTheMoney": false
        }
      ]
    }
  ]
}