{
  "symbol": "PCAR",
  "fetchedAt": "2026-04-21T04:26:46.738Z",
  "currentPrice": 128.31,
  "expirations": [
    {
      "expiration": "2027-01-15",
      "selectionReason": "leap",
      "coveredCalls": [
        {
          "label": "conservative",
          "anchor": "p25",
          "anchorPrice": 136.62271269263692,
          "contract": {
            "contractSymbol": "PCAR270115C00137000",
            "expiration": "2027-01-15",
            "daysToExpiry": 269,
            "strike": 137,
            "bid": 6.1,
            "ask": 9.2,
            "lastPrice": 11.23,
            "volume": 0,
            "openInterest": 4,
            "impliedVolatility": 0.28833719482421866,
            "inTheMoney": false
          },
          "snapWarning": false,
          "shortDated": false,
          "staticReturnPct": 0.05513206953802189,
          "staticAnnualizedPct": 0.07480745494936056,
          "assignedReturnPct": 0.12285866917951513,
          "assignedAnnualizedPct": 0.16670414219525287,
          "effectiveCostBasis": 122.21000000000001,
          "effectiveDiscountPct": 0.0475411113708986
        }
      ],
      "puts": [
        {
          "label": "deep-value",
          "anchor": "p25",
          "anchorPrice": 136.62271269263692,
          "contract": {
            "contractSymbol": "PCAR270115P00125600",
            "expiration": "2027-01-15",
            "daysToExpiry": 269,
            "strike": 125.6,
            "bid": 9.7,
            "ask": 11.4,
            "lastPrice": 11.7,
            "volume": 1,
            "openInterest": 3,
            "impliedVolatility": 0.29264013031005853,
            "inTheMoney": false
          },
          "snapWarning": false,
          "shortDated": false,
          "notAssignedReturnPct": 0.07722929936305732,
          "notAssignedAnnualizedPct": 0.10479068500935287,
          "effectiveCostBasis": 115.89999999999999,
          "effectiveDiscountPct": 0.09671888395292659,
          "inTheMoney": false
        }
      ]
    },
    {
      "expiration": "2028-01-21",
      "selectionReason": "leap",
      "coveredCalls": [
        {
          "label": "conservative",
          "anchor": "p25",
          "anchorPrice": 136.62271269263692,
          "contract": {
            "contractSymbol": "PCAR280121C00138600",
            "expiration": "2028-01-21",
            "daysToExpiry": 640,
            "strike": 138.6,
            "bid": 12.7,
            "ask": 17,
            "lastPrice": 10,
            "volume": 0,
            "openInterest": 1,
            "impliedVolatility": 0.31061480407714837,
            "inTheMoney": false
          },
          "snapWarning": false,
          "shortDated": false,
          "staticReturnPct": 0.11703930736842598,
          "staticAnnualizedPct": 0.06674897998355545,
          "assignedReturnPct": 0.19723570671376142,
          "assignedAnnualizedPct": 0.11248598898519206,
          "effectiveCostBasis": 115.61,
          "effectiveDiscountPct": 0.09897903514924791
        }
      ],
      "puts": [
        {
          "label": "deep-value",
          "anchor": "p25",
          "anchorPrice": 136.62271269263692,
          "contract": {
            "contractSymbol": "PCAR280121P00118600",
            "expiration": "2028-01-21",
            "daysToExpiry": 640,
            "strike": 118.6,
            "bid": 10.5,
            "ask": 15.5,
            "lastPrice": 14.38,
            "volume": 0,
            "openInterest": 1,
            "impliedVolatility": 0.3086006640625,
            "inTheMoney": false
          },
          "snapWarning": true,
          "shortDated": false,
          "notAssignedReturnPct": 0.08853288364249579,
          "notAssignedAnnualizedPct": 0.05049141020236088,
          "effectiveCostBasis": 108.1,
          "effectiveDiscountPct": 0.15750915750915756,
          "inTheMoney": false
        }
      ]
    }
  ]
}