{
  "symbol": "T",
  "fetchedAt": "2026-04-21T03:34:11.934Z",
  "currentPrice": 26.18,
  "expirations": [
    {
      "expiration": "2027-01-15",
      "selectionReason": "leap",
      "coveredCalls": [
        {
          "label": "aggressive",
          "anchor": "median",
          "anchorPrice": 28.01275928461912,
          "contract": {
            "contractSymbol": "T270115C00030000",
            "expiration": "2027-01-15",
            "daysToExpiry": 269,
            "strike": 30,
            "bid": 0.92,
            "ask": 1,
            "lastPrice": 1,
            "volume": 583,
            "openInterest": 46121,
            "impliedVolatility": 0.2551344018554688,
            "inTheMoney": false
          },
          "snapWarning": true,
          "shortDated": false,
          "staticReturnPct": 0.06638954843705851,
          "staticAnnualizedPct": 0.09008247278634333,
          "assignedReturnPct": 0.21230245905585146,
          "assignedAnnualizedPct": 0.2880683923992037,
          "effectiveCostBasis": 25.259999999999998,
          "effectiveDiscountPct": 0.03514132925897632
        },
        {
          "label": "stretch",
          "anchor": "p75",
          "anchorPrice": 31.727796837999723,
          "contract": {
            "contractSymbol": "T270115C00032000",
            "expiration": "2027-01-15",
            "daysToExpiry": 269,
            "strike": 32,
            "bid": 0.54,
            "ask": 0.6,
            "lastPrice": 0.58,
            "volume": 65,
            "openInterest": 10225,
            "impliedVolatility": 0.25220474365234374,
            "inTheMoney": false
          },
          "snapWarning": false,
          "shortDated": false,
          "staticReturnPct": 0.05187465156922046,
          "staticAnnualizedPct": 0.07038753837459283,
          "assignedReturnPct": 0.2741817562292663,
          "assignedAnnualizedPct": 0.3720310075229822,
          "effectiveCostBasis": 25.64,
          "effectiveDiscountPct": 0.020626432391138275
        }
      ],
      "puts": [
        {
          "label": "stretch",
          "anchor": "p75",
          "anchorPrice": 31.727796837999723,
          "contract": {
            "contractSymbol": "T270115P00030000",
            "expiration": "2027-01-15",
            "daysToExpiry": 269,
            "strike": 30,
            "bid": 4.25,
            "ask": 4.75,
            "lastPrice": 4.49,
            "volume": 20,
            "openInterest": 2380,
            "impliedVolatility": 0.24658956542968752,
            "inTheMoney": true
          },
          "snapWarning": true,
          "shortDated": false,
          "notAssignedReturnPct": 0.14166666666666666,
          "notAssignedAnnualizedPct": 0.19222428748451054,
          "effectiveCostBasis": 25.75,
          "effectiveDiscountPct": 0.016424751718869354,
          "inTheMoney": true
        },
        {
          "label": "aggressive",
          "anchor": "median",
          "anchorPrice": 28.01275928461912,
          "contract": {
            "contractSymbol": "T270115P00027000",
            "expiration": "2027-01-15",
            "daysToExpiry": 269,
            "strike": 27,
            "bid": 2.61,
            "ask": 2.83,
            "lastPrice": 2.66,
            "volume": 100,
            "openInterest": 9571,
            "impliedVolatility": 0.26343510009765625,
            "inTheMoney": true
          },
          "snapWarning": false,
          "shortDated": false,
          "notAssignedReturnPct": 0.09666666666666666,
          "notAssignedAnnualizedPct": 0.1311648079306072,
          "effectiveCostBasis": 24.39,
          "effectiveDiscountPct": 0.06837280366692128,
          "inTheMoney": true
        },
        {
          "label": "deep-value",
          "anchor": "p25",
          "anchorPrice": 20.542879040000003,
          "contract": {
            "contractSymbol": "T270115P00020000",
            "expiration": "2027-01-15",
            "daysToExpiry": 269,
            "strike": 20,
            "bid": 0.51,
            "ask": 0.75,
            "lastPrice": 0.5,
            "volume": 5,
            "openInterest": 11122,
            "impliedVolatility": 0.36084623535156246,
            "inTheMoney": false
          },
          "snapWarning": false,
          "shortDated": false,
          "notAssignedReturnPct": 0.025500000000000002,
          "notAssignedAnnualizedPct": 0.0346003717472119,
          "effectiveCostBasis": 19.49,
          "effectiveDiscountPct": 0.2555385790679909,
          "inTheMoney": false
        }
      ]
    },
    {
      "expiration": "2028-01-21",
      "selectionReason": "leap",
      "coveredCalls": [
        {
          "label": "aggressive",
          "anchor": "median",
          "anchorPrice": 28.01275928461912,
          "contract": {
            "contractSymbol": "T280121C00030000",
            "expiration": "2028-01-21",
            "daysToExpiry": 640,
            "strike": 30,
            "bid": 1.89,
            "ask": 2.07,
            "lastPrice": 2.03,
            "volume": 13,
            "openInterest": 4328,
            "impliedVolatility": 0.24842060180664063,
            "inTheMoney": false
          },
          "snapWarning": true,
          "shortDated": false,
          "staticReturnPct": 0.146537718848436,
          "staticAnnualizedPct": 0.08357229278074865,
          "assignedReturnPct": 0.292450629467229,
          "assignedAnnualizedPct": 0.16678824961802904,
          "effectiveCostBasis": 24.29,
          "effectiveDiscountPct": 0.07219251336898395
        },
        {
          "label": "stretch",
          "anchor": "p75",
          "anchorPrice": 31.727796837999723,
          "contract": {
            "contractSymbol": "T280121C00032000",
            "expiration": "2028-01-21",
            "daysToExpiry": 640,
            "strike": 32,
            "bid": 1.29,
            "ask": 1.67,
            "lastPrice": 1.5,
            "volume": 16,
            "openInterest": 3292,
            "impliedVolatility": 0.25623302368164064,
            "inTheMoney": false
          },
          "snapWarning": false,
          "shortDated": false,
          "staticReturnPct": 0.12361946063606016,
          "staticAnnualizedPct": 0.07050172364400306,
          "assignedReturnPct": 0.345926565296106,
          "assignedAnnualizedPct": 0.19728624427043545,
          "effectiveCostBasis": 24.89,
          "effectiveDiscountPct": 0.0492742551566081
        }
      ],
      "puts": [
        {
          "label": "stretch",
          "anchor": "p75",
          "anchorPrice": 31.727796837999723,
          "contract": {
            "contractSymbol": "T280121P00030000",
            "expiration": "2028-01-21",
            "daysToExpiry": 640,
            "strike": 30,
            "bid": 5.3,
            "ask": 5.75,
            "lastPrice": 5.5,
            "volume": 100,
            "openInterest": 3639,
            "impliedVolatility": 0.23828886718749998,
            "inTheMoney": true
          },
          "snapWarning": true,
          "shortDated": false,
          "notAssignedReturnPct": 0.17666666666666667,
          "notAssignedAnnualizedPct": 0.10075520833333333,
          "effectiveCostBasis": 24.7,
          "effectiveDiscountPct": 0.05653170359052714,
          "inTheMoney": true
        },
        {
          "label": "aggressive",
          "anchor": "median",
          "anchorPrice": 28.01275928461912,
          "contract": {
            "contractSymbol": "T280121P00027000",
            "expiration": "2028-01-21",
            "daysToExpiry": 640,
            "strike": 27,
            "bid": 2.74,
            "ask": 4,
            "lastPrice": 3.7,
            "volume": 210,
            "openInterest": 250,
            "impliedVolatility": 0.2557447473144532,
            "inTheMoney": true
          },
          "snapWarning": false,
          "shortDated": false,
          "notAssignedReturnPct": 0.10148148148148149,
          "notAssignedAnnualizedPct": 0.05787615740740741,
          "effectiveCostBasis": 24.259999999999998,
          "effectiveDiscountPct": 0.07333842627960281,
          "inTheMoney": true
        },
        {
          "label": "deep-value",
          "anchor": "p25",
          "anchorPrice": 20.542879040000003,
          "contract": {
            "contractSymbol": "T280121P00020000",
            "expiration": "2028-01-21",
            "daysToExpiry": 640,
            "strike": 20,
            "bid": 1.11,
            "ask": 1.55,
            "lastPrice": 1.15,
            "volume": 152,
            "openInterest": 2356,
            "impliedVolatility": 0.3225165405273437,
            "inTheMoney": false
          },
          "snapWarning": false,
          "shortDated": false,
          "notAssignedReturnPct": 0.05550000000000001,
          "notAssignedAnnualizedPct": 0.031652343750000006,
          "effectiveCostBasis": 18.89,
          "effectiveDiscountPct": 0.2784568372803667,
          "inTheMoney": false
        }
      ]
    }
  ]
}